vault_secrets/__init__.py
vault_secrets/client.py
snoogle13_vault_secrets-0.1.9.dist-info/METADATA
snoogle13_vault_secrets-0.1.9.dist-info/WHEEL
snoogle13_vault_secrets-0.1.9.dist-info/top_level.txt
snoogle13_vault_secrets-0.1.9.dist-info/RECORD
