Metadata-Version: 2.4
Name: snoogle13-vault-secrets
Version: 0.1.9
Summary: Retrieve secrets from HashiCorp Vault using AppRole authentication.
Author-email: Thomas Bassett <thomas@leospokevault.co.uk>
Requires-Python: >=3.7
Requires-Dist: hvac>=1.2.0
